standard_playing_card/__init__.py
standard_playing_card/card.py
standard_playing_card-0.0.3.dist-info/licenses/LICENSE
standard_playing_card-0.0.3.dist-info/METADATA
standard_playing_card-0.0.3.dist-info/WHEEL
standard_playing_card-0.0.3.dist-info/top_level.txt
standard_playing_card-0.0.3.dist-info/RECORD
