Metadata-Version: 2.4
Name: standard_playing_card
Version: 0.0.3
Summary: A Python module for creating French-suited standard playing card.
Author-email: Peter Dang <peterhdangg@gmail.com>
License-Expression: MIT
Project-URL: Homepage, https://github.com/pypa/sampleproject
Project-URL: Issues, https://github.com/pypa/sampleproject/issues
Classifier: Programming Language :: Python :: 3
Classifier: Operating System :: OS Independent
Requires-Python: >=3.9
License-File: LICENSE
Dynamic: license-file
